{
  "updated_at": "2025-11-01T06:13:29.151Z",
  "tokens": [
    {
      "symbol": "EUL",
      "symbol_cmc": "EUL",
      "venue": "",
      "asset_pair": "EULUSDT",
      "alert_date": "2025-10-31",
      "source": "history",
      "price": 8.616489,
      "d24": -0.38019158,
      "d7": 10.43478627,
      "d30": -8.12815803,
      "d1y": null,
      "mc": 178355787.472388,
      "tvl": 1624604996.161674,
      "mc_tvl": 0.11,
      "volume_24h": 17048817.24626968,
      "vol_mc_24": 9.558881,
      "vol7_avg": 109712.372857,
      "vol30_avg": 73564.56,
      "vol7_tvl": 0.006753,
      "var_vol_7_over_30": 1.49,
      "rsi_d": 50.684724,
      "rsi_h4": 50.933436,
      "ath": 16.985,
      "ath_date": "2025-07-09",
      "ath_mc": 351578573.113667,
      "x_ath_mc": 1.97,
      "price_target_ath_mc": 16.985,
      "circulating_supply": 20699356.67434014,
      "total_supply": 27182818.28459045,
      "max_supply": 27182818.28459045,
      "fdv": 234220465.74,
      "rank": 192,
      "sector": "Lending",
      "tags": [],
      "blurb": "Euler V2 — protocole Lending sur Ethereum, Plasma",
      "website": null,
      "twitter": null,
      "whitepaper": null,
      "date_added": null,
      "llama_category": "Lending",
      "llama_chains": [
        "Ethereum",
        "Plasma",
        "Avalanche",
        "Arbitrum",
        "Linea",
        "Binance",
        "TAC",
        "Sonic",
        "Swellchain",
        "Base",
        "Unichain",
        "Berachain",
        "BOB",
        "Mantle"
      ],
      "protocol_name": "Euler V2",
      "name": null,
      "slug": null,
      "tvl_source": "protocol:euler-v2"
    },
    {
      "symbol": "AI16Z",
      "symbol_cmc": "AI16Z",
      "venue": "",
      "asset_pair": "AI16ZUSDT",
      "alert_date": "2025-10-31",
      "source": "history",
      "price": 0.084928,
      "d24": 41.82468878,
      "d7": 39.32613976,
      "d30": -10.30178804,
      "d1y": null,
      "mc": 93420187.724515,
      "tvl": null,
      "mc_tvl": null,
      "volume_24h": 251564840.79194304,
      "vol_mc_24": 269.283168,
      "vol7_avg": 6492529.805714,
      "vol30_avg": 3481213.119333,
      "vol7_tvl": null,
      "var_vol_7_over_30": 1.87,
      "rsi_d": 58.378468,
      "rsi_h4": 68.243398,
      "ath": 2.5145,
      "ath_date": "2025-01-02",
      "ath_mc": 2765926384.143093,
      "x_ath_mc": 29.61,
      "price_target_ath_mc": 2.5145,
      "circulating_supply": 1099990608.1300826,
      "total_supply": 1099990608.1300826,
      "max_supply": 1099999958.01,
      "fdv": 93420981.79,
      "rank": 332,
      "sector": null,
      "tags": [],
      "blurb": null,
      "website": null,
      "twitter": null,
      "whitepaper": null,
      "date_added": null,
      "llama_category": null,
      "llama_chains": [],
      "protocol_name": null,
      "name": null,
      "slug": null,
      "tvl_source": null
    },
    {
      "symbol": "VELODROME",
      "symbol_cmc": "VELODROME",
      "venue": "",
      "asset_pair": "VELODROMEUSDT",
      "alert_date": "2025-10-31",
      "source": "history",
      "price": null,
      "d24": null,
      "d7": null,
      "d30": null,
      "d1y": null,
      "mc": null,
      "tvl": 31397603.68169,
      "mc_tvl": null,
      "volume_24h": null,
      "vol_mc_24": null,
      "vol7_avg": 21653520.857143,
      "vol30_avg": 13057504.293,
      "vol7_tvl": 68.965521,
      "var_vol_7_over_30": 1.66,
      "rsi_d": 55.371243,
      "rsi_h4": 65.40409,
      "ath": 0.448,
      "ath_date": "2024-12-13",
      "ath_mc": null,
      "x_ath_mc": null,
      "price_target_ath_mc": null,
      "circulating_supply": null,
      "total_supply": null,
      "max_supply": null,
      "fdv": null,
      "rank": null,
      "sector": "Dexs",
      "tags": [],
      "blurb": "Velodrome V2 — protocole Dexs sur Optimism, Swellchain",
      "website": null,
      "twitter": null,
      "whitepaper": null,
      "date_added": null,
      "llama_category": "Dexs",
      "llama_chains": [
        "Optimism",
        "Swellchain",
        "Ink",
        "Fraxtal",
        "BOB",
        "Mode",
        "Lisk",
        "Soneium",
        "Superseed",
        "Unichain"
      ],
      "protocol_name": "Velodrome V2",
      "name": null,
      "slug": null,
      "tvl_source": "protocol:velodrome-v2"
    },
    {
      "symbol": "CLOUD",
      "symbol_cmc": "CLOUD",
      "venue": "",
      "asset_pair": "CLOUDUSDT",
      "alert_date": "2025-10-30",
      "source": "history",
      "price": 0.118209,
      "d24": -1.55598308,
      "d7": -14.57538159,
      "d30": -17.09026049,
      "d1y": null,
      "mc": 0,
      "tvl": 1935984547.291621,
      "mc_tvl": null,
      "volume_24h": 1371556.06237598,
      "vol_mc_24": null,
      "vol7_avg": 534886.002857,
      "vol30_avg": 623788.235667,
      "vol7_tvl": 0.027629,
      "var_vol_7_over_30": 0.86,
      "rsi_d": 42.867852,
      "rsi_h4": 34.333477,
      "ath": 0.6457,
      "ath_date": "2024-11-14",
      "ath_mc": 0,
      "x_ath_mc": 5.46,
      "price_target_ath_mc": 0.6457,
      "circulating_supply": 0,
      "total_supply": 1000000000,
      "max_supply": 1000000000,
      "fdv": 118209146.97,
      "rank": 3778,
      "sector": "Liquid Staking",
      "tags": [],
      "blurb": "Sanctum Validator LSTs — protocole Liquid Staking sur Solana",
      "website": null,
      "twitter": null,
      "whitepaper": null,
      "date_added": null,
      "llama_category": "Liquid Staking",
      "llama_chains": [
        "Solana"
      ],
      "protocol_name": "Sanctum Validator LSTs",
      "name": null,
      "slug": null,
      "tvl_source": "protocol:sanctum-validator-lsts"
    },
    {
      "symbol": "HNT",
      "symbol_cmc": "HNT",
      "venue": "",
      "asset_pair": "HNTUSDT",
      "alert_date": "2025-10-30",
      "source": "history",
      "price": 2.517855,
      "d24": 0.852478,
      "d7": 28.96283126,
      "d30": -6.28996311,
      "d1y": null,
      "mc": 469130370.499096,
      "tvl": null,
      "mc_tvl": null,
      "volume_24h": 20970546.49623236,
      "vol_mc_24": 4.470089,
      "vol7_avg": 769135.052857,
      "vol30_avg": 617828.492667,
      "vol7_tvl": null,
      "var_vol_7_over_30": 1.24,
      "rsi_d": 62.723359,
      "rsi_h4": 60.105418,
      "ath": 10.582,
      "ath_date": "2024-12-16",
      "ath_mc": 1971653460.04773,
      "x_ath_mc": 4.2,
      "price_target_ath_mc": 10.582,
      "circulating_supply": 186321438.2959488,
      "total_supply": 186321438.2959488,
      "max_supply": 223000000,
      "fdv": 561481671.56,
      "rank": 112,
      "sector": "Chain",
      "tags": [],
      "blurb": "Helium — protocole Chain sur ",
      "website": null,
      "twitter": null,
      "whitepaper": null,
      "date_added": null,
      "llama_category": "Chain",
      "llama_chains": [],
      "protocol_name": "Helium",
      "name": null,
      "slug": null,
      "tvl_source": "protocol:helium"
    },
    {
      "symbol": "TRUMP",
      "symbol_cmc": "TRUMP",
      "venue": "",
      "asset_pair": "TRUMPUSDT",
      "alert_date": "2025-10-30",
      "source": "history",
      "price": 8.321967,
      "d24": 3.89235086,
      "d7": 39.9538367,
      "d30": 7.72169917,
      "d1y": null,
      "mc": 1664386999.01405,
      "tvl": null,
      "mc_tvl": null,
      "volume_24h": 1123048702.4130652,
      "vol_mc_24": 67.475215,
      "vol7_avg": 4042806.08,
      "vol30_avg": 1876325.483667,
      "vol7_tvl": null,
      "var_vol_7_over_30": 2.15,
      "rsi_d": 65.120362,
      "rsi_h4": 62.401518,
      "ath": 78,
      "ath_date": "2025-01-19",
      "ath_mc": 15599940626.569572,
      "x_ath_mc": 9.37,
      "price_target_ath_mc": 78,
      "circulating_supply": 199999238.802174,
      "total_supply": 999999265.71495,
      "max_supply": 999999993.45,
      "fdv": 8321966613.88,
      "rank": 49,
      "sector": "Meme",
      "tags": [],
      "blurb": "Official Trump — protocole Meme sur ",
      "website": null,
      "twitter": null,
      "whitepaper": null,
      "date_added": null,
      "llama_category": "Meme",
      "llama_chains": [],
      "protocol_name": "Official Trump",
      "name": null,
      "slug": null,
      "tvl_source": "protocol:official-trump"
    },
    {
      "symbol": "AIXBT",
      "symbol_cmc": "AIXBT",
      "venue": "",
      "asset_pair": "AIXBTUSDT",
      "alert_date": "2025-10-30",
      "source": "history",
      "price": 0.085514,
      "d24": 21.83044839,
      "d7": 37.92482012,
      "d30": -12.90053658,
      "d1y": null,
      "mc": 85380556.621409,
      "tvl": null,
      "mc_tvl": null,
      "volume_24h": 121409456.91469978,
      "vol_mc_24": 142.198015,
      "vol7_avg": 112170091.648571,
      "vol30_avg": 64860190.98,
      "vol7_tvl": null,
      "var_vol_7_over_30": 1.73,
      "rsi_d": 55.24275,
      "rsi_h4": 60.867293,
      "ath": 0.9659,
      "ath_date": "2025-01-15",
      "ath_mc": 964390977.617721,
      "x_ath_mc": 11.3,
      "price_target_ath_mc": 0.9659,
      "circulating_supply": 998437703.3002597,
      "total_supply": 998914867.3841392,
      "max_supply": 1000000000,
      "fdv": 85514155.1,
      "rank": 350,
      "sector": null,
      "tags": [],
      "blurb": null,
      "website": null,
      "twitter": null,
      "whitepaper": null,
      "date_added": null,
      "llama_category": null,
      "llama_chains": [],
      "protocol_name": null,
      "name": null,
      "slug": null,
      "tvl_source": null
    },
    {
      "symbol": "ME",
      "symbol_cmc": "ME",
      "venue": "",
      "asset_pair": "MEUSDT",
      "alert_date": "2025-10-30",
      "source": "history",
      "price": 0.455147,
      "d24": 4.02089092,
      "d7": 5.02979632,
      "d30": -26.89131619,
      "d1y": null,
      "mc": 76069140.432977,
      "tvl": 96198178.852771,
      "mc_tvl": 0.79,
      "volume_24h": 13430869.19584514,
      "vol_mc_24": 17.656134,
      "vol7_avg": 4495113.795714,
      "vol30_avg": 1873746.402,
      "vol7_tvl": 4.672764,
      "var_vol_7_over_30": 2.4,
      "rsi_d": 45.420821,
      "rsi_h4": 52.335635,
      "ath": 30,
      "ath_date": "2024-12-10",
      "ath_mc": 5013930589.42362,
      "x_ath_mc": 65.91,
      "price_target_ath_mc": 30,
      "circulating_supply": 167131019.647454,
      "total_supply": 999994697.598017,
      "max_supply": 1000000000,
      "fdv": 455146750.1,
      "rank": 379,
      "sector": "Canonical Bridge",
      "tags": [],
      "blurb": "Metis Bridge — protocole Canonical Bridge sur Ethereum",
      "website": null,
      "twitter": null,
      "whitepaper": null,
      "date_added": null,
      "llama_category": "Canonical Bridge",
      "llama_chains": [
        "Ethereum"
      ],
      "protocol_name": "Metis Bridge",
      "name": null,
      "slug": null,
      "tvl_source": "protocol:metis-bridge"
    },
    {
      "symbol": "PEAQ",
      "symbol_cmc": "PEAQ",
      "venue": "",
      "asset_pair": "PEAQUSDT",
      "alert_date": "2025-10-30",
      "source": "history",
      "price": 0.081747,
      "d24": -0.37520479,
      "d7": -8.27059679,
      "d30": -35.69232254,
      "d1y": null,
      "mc": 116597322.333088,
      "tvl": null,
      "mc_tvl": null,
      "volume_24h": 8109666.26521187,
      "vol_mc_24": 6.955277,
      "vol7_avg": 6079533.594286,
      "vol30_avg": 5806039.368333,
      "vol7_tvl": null,
      "var_vol_7_over_30": 1.05,
      "rsi_d": 45.181584,
      "rsi_h4": 45.556893,
      "ath": 0.7551,
      "ath_date": "2024-12-10",
      "ath_mc": 1077007454.525212,
      "x_ath_mc": 9.24,
      "price_target_ath_mc": 0.7551,
      "circulating_supply": 1426311024.401022,
      "total_supply": 4337999017.594352,
      "max_supply": null,
      "fdv": 354620458.71,
      "rank": 289,
      "sector": "Chain",
      "tags": [],
      "blurb": "peaq — protocole Chain sur ",
      "website": null,
      "twitter": null,
      "whitepaper": null,
      "date_added": null,
      "llama_category": "Chain",
      "llama_chains": [],
      "protocol_name": "peaq",
      "name": null,
      "slug": null,
      "tvl_source": "protocol:peaq"
    },
    {
      "symbol": "SOLV",
      "symbol_cmc": "SOLV",
      "venue": "",
      "asset_pair": "SOLVUSDT",
      "alert_date": "2025-10-30",
      "source": "history",
      "price": 0.01954,
      "d24": -0.87714776,
      "d7": 9.25652038,
      "d30": -53.73456833,
      "d1y": null,
      "mc": 28970180.743519,
      "tvl": 1108177778.203602,
      "mc_tvl": 0.03,
      "volume_24h": 33903330.74818428,
      "vol_mc_24": 117.028372,
      "vol7_avg": 146647698.998571,
      "vol30_avg": 152036364.429667,
      "vol7_tvl": 13.233229,
      "var_vol_7_over_30": 0.96,
      "rsi_d": 38.494171,
      "rsi_h4": 58.512499,
      "ath": 0.19474,
      "ath_date": "2025-01-17",
      "ath_mc": 288721524,
      "x_ath_mc": 9.97,
      "price_target_ath_mc": 0.19474,
      "circulating_supply": 1482600000,
      "total_supply": 8400000000,
      "max_supply": 9660000000,
      "fdv": 188757551.59,
      "rank": 692,
      "sector": "Bridge",
      "tags": [],
      "blurb": "SolvBTC — protocole Bridge sur Bitcoin, Ethereum",
      "website": null,
      "twitter": null,
      "whitepaper": null,
      "date_added": null,
      "llama_category": "Bridge",
      "llama_chains": [
        "Bitcoin",
        "Ethereum",
        "Binance",
        "Arbitrum",
        "Base",
        "Avalanche",
        "Mantle",
        "Polygon",
        "Merlin",
        "BOB"
      ],
      "protocol_name": "SolvBTC",
      "name": null,
      "slug": null,
      "tvl_source": "protocol:solvbtc"
    }
  ]
}